benchmarks/__init__.py
benchmarks/benchmark_func.py
benchmarks/pqp_benchmark.py
benchmarks/returns_benchmark.py
munin/README.md
munin/__init__.py
munin/generate_report.py
munin/plugins.py
munin/templates/classification_report_template.html
munin/templates/confusion_matrix.html
munin/templates/head.html
munin/templates/metrics.html
munin/templates/prc.html
munin/templates/predictions.html
munin/templates/roc.html
munin/utilities/__init__.py
munin/utilities/html_embeddings.py
tests/__init__.py
tests/test_imports.py
tests/test_report.py
tests/test_sanity.py
Munin-0.2.4.dist-info/LICENSE.md
Munin-0.2.4.dist-info/METADATA
Munin-0.2.4.dist-info/WHEEL
Munin-0.2.4.dist-info/entry_points.txt
Munin-0.2.4.dist-info/top_level.txt
Munin-0.2.4.dist-info/RECORD
